moorse/__init__.py
moorse/moorse.py
moorse-0.0.4.dist-info/LICENSE
moorse-0.0.4.dist-info/METADATA
moorse-0.0.4.dist-info/WHEEL
moorse-0.0.4.dist-info/top_level.txt
moorse-0.0.4.dist-info/RECORD
