Metadata-Version: 2.1
Name: moorse
Version: 0.0.4
Summary: A sdk that allows Moorse customers to write some simplified calls to the Moorse resources.
Home-page: https://moorse.io
Author: Moorse.io
Author-email: douglas.alv.sousa@gmail.com
License: MIT
Keywords: DEVELOPMENT KIT,MOORSE,SDK
Classifier: Development Status :: 3 - Alpha
Classifier: Intended Audience :: Developers
Classifier: Topic :: Software Development :: Build Tools
Classifier: License :: OSI Approved :: MIT License
Classifier: Programming Language :: Python :: 3
Classifier: Programming Language :: Python :: 3.4
Classifier: Programming Language :: Python :: 3.5
Classifier: Programming Language :: Python :: 3.6
Classifier: Programming Language :: Python :: 3.9
Classifier: Programming Language :: Python :: 3.10
License-File: LICENSE
